{
  "pools": [
    {
      "rolls": 1,
      "entries": [
        {
          "type": "minecraft:item",
          "name": "minecraft:tropical_fish",
          "functions": [
            {
              "function": "minecraft:set_nbt",
              "tag": "{CustomModelData:8361001,sanguine:{id:\"chevon_jerky\"},manic:{sanity:\"very_good\"}}"
            },
            {
              "function": "minecraft:set_lore",
              "lore": [
                {
                  "translate": "pack.sanguine",
                  "color": "#880f0f",
                  "italic": true
                }
              ]
            },
            {
              "function": "minecraft:set_name",
              "name": {
                "translate": "item.sanguine.chevon_jerky",
                "color": "white",
                "italic": false
              }
            }
          ]
        }
      ]
    }
  ]
}
