{
  "pools": [
    {
      "rolls": 1,
      "entries": [
        {
          "type": "minecraft:item",
          "name": "minecraft:splash_potion",
          "functions": [
            {
              "function": "minecraft:set_nbt",
              "tag": "{CustomPotionColor:10397484,HideFlags:32,sanguine:{id:\"splash_potion_recklessness_extended\"},nucleus:{potion:{can_linger:1b}},custom_potion_effects:[{id:\"minecraft:haste\",amplifier:1b,duration:9600},{id:\"minecraft:hunger\",amplifier:2b,duration:9600}]}"
            },
            {
              "function": "minecraft:set_lore",
              "lore": [
                {
                  "translate": "potion.withDuration",
                  "color": "#db5853",
                  "italic": false,
                  "with": [
                    {"translate":"potion.withAmplifier","with":[{"translate":"effect.minecraft.hunger"},{"translate":"potion.potency.2"}]},
                    {"text":"08:00"}
                  ]
                },
                {
                  "translate": "potion.withDuration",
                  "color": "#c99993",
                  "italic": false,
                  "with": [
                    {"translate":"potion.withAmplifier","with":[{"translate":"effect.minecraft.haste"},{"translate":"potion.potency.1"}]},
                    {"text":"08:00"}
                  ]
                },
                {
                  "translate": "sanguine.tooltip",
                  "font": "sanguine:tooltip",
                  "color": "white",
                  "italic": false,
                  "with": [
                    {"translate":"pack.sanguine","font":"minecraft:default","color":"#880f0f","italic":true}
                  ]
                },
                "",
                {
                  "translate": "potion.whenDrank",
                  "color": "gray",
                  "italic": false
                },
                {
                  "translate": "attribute.modifier.plus.1",
                  "italic": false,
                  "color": "#c99993",
                  "with": [
                    20,
                    {
                      "translate": "attribute.name.generic.attack_speed"
                    }
                  ]
                }
              ]
            },
            {
              "function": "minecraft:set_name",
              "name": {
                "translate": "item.sanguine.splash_potion.effect.recklessness",
                "color": "white",
                "italic": false
              }
            }
          ]
        }
      ]
    }
  ]
}
